{"author_date.qmd":[],"harmonized_fennica.qmd":[],"ai_sauna.qmd":[],"publication_frequency.qmd":[],"publication_time.qmd":[],"title.qmd":[],"author_info.qmd":[],"kanto_author_info.qmd":[],"physical_dimensions.qmd":[],"signum.qmd":[],"acknowledgments.qmd":[],"title_remainder.qmd":[],"title_uniform.qmd":[],"publication_place.qmd":[],"publisher.qmd":[],"genre_655.qmd":[],"genre_008.qmd":[],"title2.qmd":[],"technical_information.qmd":[],"udk.qmd":[],"language.qmd":[],"author_name.qmd":[],"index.qmd":[],"content_type.qmd":[]}
