{"publication_place.qmd":[],"publication_frequency.qmd":[],"harmonized_fennica.qmd":[],"physical_dimensions.qmd":[],"publisher.qmd":[],"technical_information.qmd":[],"signum.qmd":[],"content_type.qmd":[],"title_uniform.qmd":[],"genre_008.qmd":[],"publication_time.qmd":[],"index.qmd":[],"language.qmd":[],"author_date.qmd":[],"title.qmd":[],"title_remainder.qmd":[],"author_info.qmd":[],"author_name.qmd":[],"acknowledgments.qmd":[],"udk.qmd":[],"ai_sauna.qmd":[],"genre_655.qmd":[],"title2.qmd":[],"kanto_author_info.qmd":[]}
